{
    "result": [
        {
            "values": [
                {
                    "key": "linia",
                    "value": "203"
                }
            ]
        },
        {
            "values": [
                {
                    "key": "linia",
                    "value": "210"
                }
            ]
        },
        {
            "values": [
                {
                    "key": "linia",
                    "value": "156"
                }
            ]
        },
        {
            "values": [
                {
                    "key": "linia",
                    "value": "N41"
                }
            ]
        },
        {
            "values": [
                {
                    "key": "linia",
                    "value": "Z12"
                }
            ]
        },
        {
            "values": [
                {
                    "key": "linia",
                    "value": "184"
                }
            ]
        },
        {
            "values": [
                {
                    "key": "linia",
                    "value": "250"
                }
            ]
        }
    ]
}