{
    "result": [
        {
            "values": [
                {
                    "key": "linia",
                    "value": "724"
                }
            ]
        },
        {
            "values": [
                {
                    "key": "linia",
                    "value": "L39"
                }
            ]
        },
        {
            "values": [
                {
                    "key": "linia",
                    "value": "L24"
                }
            ]
        },
        {
            "values": [
                {
                    "key": "linia",
                    "value": "710"
                }
            ]
        }
    ]
}